{"resources":{"googleworkspace":{"id":"googleworkspace","name":"googleworkspace","fields":{"domains":{"name":"domains","type":"\u0019\u001bgoogleworkspace.domain","title":"Retrieves a list of domains for the Google Workspace account"},"groups":{"name":"groups","type":"\u0019\u001bgoogleworkspace.group","title":"Retrieves a list of all groups for the Google Workspace account"},"orgUnits":{"name":"orgUnits","type":"\u0019\u001bgoogleworkspace.orgUnit","title":"Retrieves a list of all organizational units for the Google Workspace account"},"roles":{"name":"roles","type":"\u0019\u001bgoogleworkspace.role","title":"Retrieves a list of all roles for the Google Workspace account"},"users":{"name":"users","type":"\u0019\u001bgoogleworkspace.user","title":"Retrieves a list of all users for the Google Workspace account"}},"title":"Google Workspace"},"googleworkspace.domain":{"id":"googleworkspace.domain","name":"googleworkspace.domain","fields":{"creationTime":{"name":"creationTime","type":"\t","is_mandatory":true,"title":"Creation time of the domain"},"domainName":{"name":"domainName","type":"\u0007","is_mandatory":true,"title":"The domain name of the customer"},"isPrimary":{"name":"isPrimary","type":"\u0004","is_mandatory":true,"title":"Indicates if the domain is a primary domain"},"verified":{"name":"verified","type":"\u0004","is_mandatory":true,"title":"Indicates the verification state of a domain"}},"title":"Google Workspace domain","private":true,"defaults":"domainName"},"googleworkspace.group":{"id":"googleworkspace.group","name":"googleworkspace.group","fields":{"adminCreated":{"name":"adminCreated","type":"\u0004","is_mandatory":true,"title":"Indicates if this group was created by an administrator rather than a user"},"aliases":{"name":"aliases","type":"\u0019\u0007","is_mandatory":true,"title":"A list of a group's alias email addresses"},"description":{"name":"description","type":"\u0007","is_mandatory":true,"title":"Purpose of the group"},"directMembersCount":{"name":"directMembersCount","type":"\u0005","is_mandatory":true,"title":"The number of users that are direct members of the group"},"email":{"name":"email","type":"\u0007","is_mandatory":true,"title":"The group's email address"},"id":{"name":"id","type":"\u0007","is_mandatory":true,"title":"The unique ID of a group"},"members":{"name":"members","type":"\u0019\u001bgoogleworkspace.member","title":"Retrieve members of the group"},"name":{"name":"name","type":"\u0007","is_mandatory":true,"title":"The group's display name"},"securitySettings":{"name":"securitySettings","type":"\n","title":"Group security settings"},"settings":{"name":"settings","type":"\n","title":"Group settings"}},"title":"Google Workspace Group","private":true,"defaults":"email"},"googleworkspace.member":{"id":"googleworkspace.member","name":"googleworkspace.member","fields":{"email":{"name":"email","type":"\u0007","is_mandatory":true,"title":"The member's email address"},"id":{"name":"id","type":"\u0007","is_mandatory":true,"title":"The unique ID of the group member"},"status":{"name":"status","type":"\u0007","is_mandatory":true,"title":"Status of member"},"type":{"name":"type","type":"\u0007","is_mandatory":true,"title":"The type of group member"},"user":{"name":"user","type":"\u001bgoogleworkspace.user","title":"Linked user account"}},"title":"Google Workpsace Group Member","private":true,"defaults":"email"},"googleworkspace.orgUnit":{"id":"googleworkspace.orgUnit","name":"googleworkspace.orgUnit","fields":{"description":{"name":"description","type":"\u0007","is_mandatory":true,"title":"Description of the organizational unit"},"id":{"name":"id","type":"\u0007","is_mandatory":true,"title":"The unique ID of the organizational unit"},"name":{"name":"name","type":"\u0007","is_mandatory":true,"title":"The organizational unit's path name"}},"title":"Google Workspace organizational unit","private":true,"defaults":"name"},"googleworkspace.report.activity":{"id":"googleworkspace.report.activity","name":"googleworkspace.report.activity","fields":{"actor":{"name":"actor","type":"\n","is_mandatory":true},"events":{"name":"events","type":"\u0019\n","is_mandatory":true},"id":{"name":"id","type":"\u0005","is_mandatory":true},"ipAddress":{"name":"ipAddress","type":"\u0007","is_mandatory":true},"ownerDomain":{"name":"ownerDomain","type":"\u0007","is_mandatory":true}},"title":"Google Workspace App Reports Activity","private":true},"googleworkspace.report.apps":{"id":"googleworkspace.report.apps","name":"googleworkspace.report.apps","fields":{"drive":{"name":"drive","type":"\u0019\u001bgoogleworkspace.report.activity"}},"title":"Google Workspace Apps Reports"},"googleworkspace.report.usage":{"id":"googleworkspace.report.usage","name":"googleworkspace.report.usage","fields":{"account":{"name":"account","type":"\n","title":"Account Settings"},"appUsage":{"name":"appUsage","type":"\n","title":"App Usage"},"customerId":{"name":"customerId","type":"\u0007","is_mandatory":true,"title":"The unique identifier of the customer's account"},"date":{"name":"date","type":"\t","is_mandatory":true,"title":"Date of the report"},"entityId":{"name":"entityId","type":"\u0007","is_mandatory":true,"title":"Google Workspace entity ID"},"parameters":{"name":"parameters","type":"\u0019\n","is_mandatory":true,"title":"Parameter value pairs"},"profileId":{"name":"profileId","type":"\u0007","is_mandatory":true,"title":"Google Workspace profile identifier"},"security":{"name":"security","type":"\n","title":"Security Settings"},"type":{"name":"type","type":"\u0007","is_mandatory":true,"title":"Entity type"},"userEmail":{"name":"userEmail","type":"\u0007","is_mandatory":true,"title":"Email of user"}},"title":"Google Workspace Usage Report","private":true},"googleworkspace.report.users":{"id":"googleworkspace.report.users","name":"googleworkspace.report.users","fields":{"list":{"name":"list","type":"\u0019\u001bgoogleworkspace.report.usage"}},"list_type":"\u001bgoogleworkspace.report.usage","title":"Google Workspace User Usage Reports"},"googleworkspace.role":{"id":"googleworkspace.role","name":"googleworkspace.role","fields":{"description":{"name":"description","type":"\u0007","is_mandatory":true,"title":"A short description of the role"},"id":{"name":"id","type":"\u0005","is_mandatory":true,"title":"ID of the role"},"isSuperAdminRole":{"name":"isSuperAdminRole","type":"\u0004","is_mandatory":true,"title":"Indicates if the role is a super admin role"},"isSystemRole":{"name":"isSystemRole","type":"\u0004","is_mandatory":true,"title":"Indicates if this is a pre-defined system role"},"name":{"name":"name","type":"\u0007","is_mandatory":true,"title":"Name of the role"},"privileges":{"name":"privileges","type":"\u0019\n","is_mandatory":true,"title":"The set of privileges"}},"title":"Google Workspace Role","private":true,"defaults":"name"},"googleworkspace.token":{"id":"googleworkspace.token","name":"googleworkspace.token","fields":{"anonymous":{"name":"anonymous","type":"\u0004","is_mandatory":true,"title":"Indicates if the application is registered with Google"},"clientId":{"name":"clientId","type":"\u0007","is_mandatory":true,"title":"The Client ID of the application"},"displayText":{"name":"displayText","type":"\u0007","is_mandatory":true,"title":"The displayable name of the application token"},"nativeApp":{"name":"nativeApp","type":"\u0004","is_mandatory":true,"title":"Indicates if the token is issued to an installed application"},"scopes":{"name":"scopes","type":"\u0019\u0007","is_mandatory":true,"title":"A list of granted authorization scopes the application"},"userKey":{"name":"userKey","type":"\u0007","is_mandatory":true,"title":"The unique ID of the user that issued the token"}},"title":"Google Workspace Token","private":true,"defaults":"displayText"},"googleworkspace.user":{"id":"googleworkspace.user","name":"googleworkspace.user","fields":{"agreedToTerms":{"name":"agreedToTerms","type":"\u0004","is_mandatory":true,"title":"User accepted the Terms of Service agreement"},"aliases":{"name":"aliases","type":"\u0019\u0007","is_mandatory":true,"title":"A list of the user's alias email addresses"},"archived":{"name":"archived","type":"\u0004","is_mandatory":true,"title":"Indicates if user is archived"},"creationTime":{"name":"creationTime","type":"\t","is_mandatory":true,"title":"User's account creation time"},"familyName":{"name":"familyName","type":"\u0007","is_mandatory":true,"title":"The user's last name"},"fullName":{"name":"fullName","type":"\u0007","is_mandatory":true,"title":"The user's full name"},"givenName":{"name":"givenName","type":"\u0007","is_mandatory":true,"title":"The user's first names"},"id":{"name":"id","type":"\u0007","is_mandatory":true,"title":"The unique ID for the user"},"isAdmin":{"name":"isAdmin","type":"\u0004","is_mandatory":true,"title":"Indicates a user with super admininistrator privileges"},"isEnforcedIn2Sv":{"name":"isEnforcedIn2Sv","type":"\u0004","is_mandatory":true,"title":"Is 2-step verification enforced"},"isEnrolledIn2Sv":{"name":"isEnrolledIn2Sv","type":"\u0004","is_mandatory":true,"title":"Is enrolled in 2-step verification"},"isMailboxSetup":{"name":"isMailboxSetup","type":"\u0004","is_mandatory":true,"title":"Indicates if the user's Google mailbox is created"},"lastLoginTime":{"name":"lastLoginTime","type":"\t","is_mandatory":true,"title":"User's last login time"},"primaryEmail":{"name":"primaryEmail","type":"\u0007","is_mandatory":true,"title":"The user's primary email address"},"recoveryEmail":{"name":"recoveryEmail","type":"\u0007","is_mandatory":true,"title":"Recovery email of the user"},"recoveryPhone":{"name":"recoveryPhone","type":"\u0007","is_mandatory":true,"title":"Recovery phone of the user"},"suspended":{"name":"suspended","type":"\u0004","is_mandatory":true,"title":"Indicates if user is suspended"},"suspensionReason":{"name":"suspensionReason","type":"\u0007","is_mandatory":true,"title":"The reason a user account is suspended"},"tokens":{"name":"tokens","type":"\u0019\u001bgoogleworkspace.token","title":"Returns the user-issued tokens to 3rd party applications"},"usageReport":{"name":"usageReport","type":"\u001bgoogleworkspace.report.usage","title":"Retrieves latest report for the user"}},"title":"Google Workspace User Accounts","private":true,"defaults":"primaryEmail"}}}